watsoncrdp.cp39-win_amd64.pyd
watsoncrdp-0.1.0.dist-info/METADATA
watsoncrdp-0.1.0.dist-info/WHEEL
watsoncrdp-0.1.0.dist-info/top_level.txt
watsoncrdp-0.1.0.dist-info/RECORD
