Metadata-Version: 2.1
Name: watsoncrdp
Version: 0.1.0
Summary: UNKNOWN
Home-page: UNKNOWN
License: UNKNOWN
Platform: UNKNOWN
Provides-Extra: dev
Requires-Dist: cython ; extra == 'dev'
